eulcommon/__init__.py
eulcommon/apps.py
eulcommon/binfile/__init__.py
eulcommon/binfile/core.py
eulcommon/binfile/eudora.py
eulcommon/binfile/outlookexpress.py
eulcommon/djangoextras/__init__.py
eulcommon/djangoextras/formfields.py
eulcommon/djangoextras/validators.py
eulcommon/djangoextras/auth/__init__.py
eulcommon/djangoextras/auth/decorators.py
eulcommon/djangoextras/http/__init__.py
eulcommon/djangoextras/http/decorators.py
eulcommon/djangoextras/http/responses.py
eulcommon/djangoextras/taskresult/__init__.py
eulcommon/djangoextras/taskresult/admin.py
eulcommon/djangoextras/taskresult/models.py
eulcommon/djangoextras/taskresult/tests.py
eulcommon/djangoextras/taskresult/urls.py
eulcommon/djangoextras/taskresult/views.py
eulcommon/djangoextras/taskresult/migrations/0001_initial.py
eulcommon/djangoextras/taskresult/migrations/__init__.py
eulcommon/djangoextras/taskresult/templates/images/check.png
eulcommon/djangoextras/taskresult/templates/images/x.png
eulcommon/djangoextras/taskresult/templates/taskresult/recent.html
eulcommon/djangoextras/taskresult/templates/taskresult/snippets/display_task.html
eulcommon/djangoextras/taskresult/templates/taskresult/snippets/task_styles.html
eulcommon/searchutil/__init__.py
eulcommon/searchutil/parsetab.py
eulcommon/searchutil/templates/searchutil/pagination.html
eulcommon/searchutil/templatetags/__init__.py
eulcommon/searchutil/templatetags/search_utils.py
eulcommon-0.19.0.dist-info/DESCRIPTION.rst
eulcommon-0.19.0.dist-info/METADATA
eulcommon-0.19.0.dist-info/metadata.json
eulcommon-0.19.0.dist-info/RECORD
eulcommon-0.19.0.dist-info/top_level.txt
eulcommon-0.19.0.dist-info/WHEEL
test/__init__.py
test/test_celery_app.py
test/test_searchutil.py
test/test_setup.py
test/test_urls.py
test/testsettings.py
