Metadata-Version: 2.0
Name: eulcommon
Version: 0.19.0
Summary: A collection of small python utilities for working with binary files and Django
Home-page: https://github.com/emory-libraries/eulcommon
Author: Emory University Libraries
Author-email: libsysdev-l@listserv.cc.emory.edu
License: Apache License, Version 2.0
Keywords: Binary data
Platform: UNKNOWN
Classifier: Development Status :: 4 - Beta
Classifier: Framework :: Django
Classifier: Intended Audience :: Developers
Classifier: License :: OSI Approved :: Apache Software License
Classifier: Natural Language :: English
Classifier: Operating System :: OS Independent
Classifier: Programming Language :: Python
Classifier: Topic :: Software Development :: Libraries :: Python Modules
Classifier: Topic :: Utilities
Requires-Dist: mimeparse
Requires-Dist: python-magic
Requires-Dist: celery
Provides-Extra: dev
Requires-Dist: mock; extra == 'dev'
Requires-Dist: ply; extra == 'dev'
Requires-Dist: pytest; extra == 'dev'
Requires-Dist: pytest-cov; extra == 'dev'
Requires-Dist: pytest-django; extra == 'dev'
Requires-Dist: django-celery; extra == 'dev'
Requires-Dist: django (<1.9); extra == 'dev'
Requires-Dist: sphinx; extra == 'dev'
Provides-Extra: test
Requires-Dist: mock; extra == 'test'
Requires-Dist: ply; extra == 'test'
Requires-Dist: pytest; extra == 'test'
Requires-Dist: pytest-cov; extra == 'test'
Requires-Dist: pytest-django; extra == 'test'
Requires-Dist: django-celery; extra == 'test'
